dm_app/__init__.py
dm_app/notifier/__init__.py
dm_app/notifier/apps.py
dm_app/notifier/filters.py
dm_app/notifier/models.py
dm_app/notifier/pagination.py
dm_app/notifier/serializers.py
dm_app/notifier/urls.py
dm_app/notifier/views.py
dm_app/notifier/migrations/0001_initial.py
dm_app/notifier/migrations/__init__.py
dm_app/notifier/tests/__init__.py
dm_app_notifier-1.0.1.dist-info/licenses/LICENSE
dm_app_notifier-1.0.1.dist-info/METADATA
dm_app_notifier-1.0.1.dist-info/WHEEL
dm_app_notifier-1.0.1.dist-info/top_level.txt
dm_app_notifier-1.0.1.dist-info/RECORD
